folium_maps/__init__.py
folium_maps/_version.py
folium_maps/elements.py
folium_maps/features.py
folium_maps/folium.py
folium_maps/map.py
folium_maps/raster_layers.py
folium_maps/utilities.py
folium_maps/vector_layers.py
folium_maps/plugins/__init__.py
folium_maps/plugins/antpath.py
folium_maps/plugins/beautify_icon.py
folium_maps/plugins/boat_marker.py
folium_maps/plugins/draw.py
folium_maps/plugins/dual_map.py
folium_maps/plugins/fast_marker_cluster.py
folium_maps/plugins/feature_group_sub_group.py
folium_maps/plugins/float_image.py
folium_maps/plugins/fullscreen.py
folium_maps/plugins/geocoder.py
folium_maps/plugins/heat_map.py
folium_maps/plugins/heat_map_withtime.py
folium_maps/plugins/locate_control.py
folium_maps/plugins/marker_cluster.py
folium_maps/plugins/measure_control.py
folium_maps/plugins/minimap.py
folium_maps/plugins/mouse_position.py
folium_maps/plugins/pattern.py
folium_maps/plugins/polyline_offset.py
folium_maps/plugins/polyline_text_path.py
folium_maps/plugins/scroll_zoom_toggler.py
folium_maps/plugins/search.py
folium_maps/plugins/semicircle.py
folium_maps/plugins/terminator.py
folium_maps/plugins/time_slider_choropleth.py
folium_maps/plugins/timestamped_geo_json.py
folium_maps/plugins/timestamped_wmstilelayer.py
folium_maps/templates/fit_bounds.js
folium_maps/templates/leaflet_heat.min.js
folium_maps/templates/pa7_hm.min.js
folium_maps/templates/pa7_leaflet_hm.min.js
folium_maps/templates/tiles/cartodbdark_matter/attr.txt
folium_maps/templates/tiles/cartodbdark_matter/tiles.txt
folium_maps/templates/tiles/cartodbpositron/attr.txt
folium_maps/templates/tiles/cartodbpositron/tiles.txt
folium_maps/templates/tiles/cartodbpositronnolabels/attr.txt
folium_maps/templates/tiles/cartodbpositronnolabels/tiles.txt
folium_maps/templates/tiles/cartodbpositrononlylabels/attr.txt
folium_maps/templates/tiles/cartodbpositrononlylabels/tiles.txt
folium_maps/templates/tiles/openstreetmap/attr.txt
folium_maps/templates/tiles/openstreetmap/tiles.txt
folium_maps-1.0.0.dist-info/LICENSE.txt
folium_maps-1.0.0.dist-info/METADATA
folium_maps-1.0.0.dist-info/WHEEL
folium_maps-1.0.0.dist-info/top_level.txt
folium_maps-1.0.0.dist-info/RECORD
